donifaranga/__init__.py
donifaranga/client.py
donifaranga/config.py
donifaranga/server.py
donifaranga/utils.py
donifaranga/models/__init__.py
donifaranga/routes/__init__.py
donifaranga-0.0.3.dist-info/LICENSE
donifaranga-0.0.3.dist-info/METADATA
donifaranga-0.0.3.dist-info/WHEEL
donifaranga-0.0.3.dist-info/top_level.txt
donifaranga-0.0.3.dist-info/RECORD
