Metadata-Version: 2.1
Name: donifaranga
Version: 0.0.3
Summary: Donifaranga is a powerful client-server package designed in the frame of Federated Learning to facilitate distributed machine learning while preserving data privacy. 
Home-page: https://github.com/adamstrvor/donifaranga
Author: Adama Seydou Traore
Author-email: adamaseydoutraore86@gmail.com
Classifier: Programming Language :: Python :: 3
Classifier: License :: OSI Approved :: MIT License
Classifier: Operating System :: OS Independent
License-File: LICENSE
